jsontyping.py
jsontyping-1.0.3.dist-info/DESCRIPTION.rst
jsontyping-1.0.3.dist-info/METADATA
jsontyping-1.0.3.dist-info/RECORD
jsontyping-1.0.3.dist-info/WHEEL
jsontyping-1.0.3.dist-info/metadata.json
jsontyping-1.0.3.dist-info/top_level.txt
