Metadata-Version: 2.0
Name: jsontyping
Version: 1.0.3
Summary: JSON support for named tuples, datetime and other objects, preventing ambiguity via type annotations
Home-page: https://github.com/m-click/jsontyping
Author: Volker Diels-Grabsch
Author-email: volker.diels-grabsch@m-click.aero
License: ISC
Keywords: json
Platform: UNKNOWN
Classifier: Development Status :: 5 - Production/Stable
Classifier: Intended Audience :: Developers
Classifier: License :: OSI Approved :: ISC License (ISCL)
Classifier: Programming Language :: Python :: 2
Classifier: Programming Language :: Python :: 3
Classifier: Topic :: Software Development :: Libraries
